src/__init__.py
src/base/API.py
src/base/__init__.py
src/base/loop.py
src/bot.py
discorsebotlib-1.0.0.dist-info/LICENSE
discorsebotlib-1.0.0.dist-info/WHEEL
discorsebotlib-1.0.0.dist-info/METADATA
discorsebotlib-1.0.0.dist-info/RECORD
