Metadata-Version: 2.1
Name: discorsebotlib
Version: 1.0.0
Summary: A bot lib for Discorse based Fourms
Author: ShowierData9978
Requires-Python: >=3.8,<4.0
Classifier: Programming Language :: Python :: 3
Classifier: Programming Language :: Python :: 3.10
Classifier: Programming Language :: Python :: 3.8
Classifier: Programming Language :: Python :: 3.9
Requires-Dist: aiohttp (>=3.8.3,<4.0.0)
